{
  "openapi": "3.0.4",
  "info": {
    "title": "Shizou.WebApi",
    "version": "1.0"
  },
  "paths": {
    "/api/Account/Login": {
      "post": {
        "tags": [
          "Account"
        ],
        "operationId": "ShizouHttpClient_AccountLogin",
        "requestBody": {
          "description": "Password",
          "content": {
            "application/json": {
              "schema": {
                "type": "string"
              }
            }
          },
          "required": true
        },
        "responses": {
          "200": {
            "description": "OK",
            "headers": {
              "Set-Cookie": {
                "description": "Sets the Identity cookie",
                "schema": {
                  "type": "string",
                  "description": "Sets the Identity cookie",
                  "format": ""
                }
              }
            }
          },
          "400": {
            "description": "Bad Request"
          }
        }
      }
    },
    "/api/Account/SetPassword": {
      "post": {
        "tags": [
          "Account"
        ],
        "operationId": "ShizouHttpClient_AccountChangePassword",
        "requestBody": {
          "content": {
            "application/json": {
              "schema": {
                "allOf": [
                  {
                    "$ref": "#/components/schemas/PasswordModel"
                  }
                ]
              }
            }
          }
        },
        "responses": {
          "200": {
            "description": "OK",
            "headers": {
              "Set-Cookie": {
                "description": "Sets the Identity cookie",
                "schema": {
                  "type": "string",
                  "description": "Sets the Identity cookie",
                  "format": ""
                }
              }
            }
          },
          "400": {
            "description": "Bad Request",
            "content": {
              "application/json": {
                "schema": {
                  "$ref": "#/components/schemas/ProblemDetails"
                }
              }
            }
          },
          "500": {
            "description": "Internal Server Error",
            "content": {
              "application/json": {
                "schema": {
                  "$ref": "#/components/schemas/ProblemDetails"
                }
              }
            }
          }
        }
      }
    },
    "/api/AniDbAnimes": {
      "get": {
        "tags": [
          "AniDbAnimes"
        ],
        "operationId": "ShizouHttpClient_AniDbAnimesGet",
        "responses": {
          "200": {
            "description": "OK",
            "content": {
              "application/json": {
                "schema": {
                  "type": "array",
                  "items": {
                    "$ref": "#/components/schemas/AniDbAnime"
                  }
                }
              }
            }
          },
          "401": {
            "description": "Unauthorized"
          }
        }
      }
    },
    "/api/AniDbAnimes/{id}": {
      "get": {
        "tags": [
          "AniDbAnimes"
        ],
        "operationId": "ShizouHttpClient_AniDbAnimesGet",
        "parameters": [
          {
            "name": "id",
            "in": "path",
            "required": true,
            "schema": {
              "type": "integer",
              "format": "int32"
            }
          }
        ],
        "responses": {
          "200": {
            "description": "OK",
            "content": {
              "application/json": {
                "schema": {
                  "$ref": "#/components/schemas/AniDbAnime"
                }
              }
            }
          },
          "404": {
            "description": "Not Found"
          },
          "401": {
            "description": "Unauthorized"
          }
        }
      }
    },
    "/api/AniDbAnimes/GetAnimeSearch": {
      "get": {
        "tags": [
          "AniDbAnimes"
        ],
        "operationId": "ShizouHttpClient_AniDbAnimesGetAnimeSearch",
        "parameters": [
          {
            "name": "query",
            "in": "query",
            "schema": {
              "type": "string"
            }
          }
        ],
        "responses": {
          "200": {
            "description": "OK",
            "content": {
              "application/json": {
                "schema": {
                  "type": "array",
                  "items": {
                    "type": "integer",
                    "format": "int32"
                  }
                }
              }
            }
          },
          "404": {
            "description": "Not Found"
          },
          "401": {
            "description": "Unauthorized"
          }
        }
      }
    },
    "/api/AniDbCredits/ByAniDbAnimeId/{id}": {
      "get": {
        "tags": [
          "AniDbCredits"
        ],
        "operationId": "ShizouHttpClient_AniDbCreditsByAniDbAnimeId",
        "parameters": [
          {
            "name": "id",
            "in": "path",
            "required": true,
            "schema": {
              "type": "integer",
              "format": "int32"
            }
          }
        ],
        "responses": {
          "200": {
            "description": "OK",
            "content": {
              "application/json": {
                "schema": {
                  "type": "array",
                  "items": {
                    "$ref": "#/components/schemas/AniDbCredit"
                  }
                }
              }
            }
          },
          "404": {
            "description": "Not Found"
          },
          "401": {
            "description": "Unauthorized"
          }
        }
      }
    },
    "/api/AniDbEpisodeFileXrefs": {
      "get": {
        "tags": [
          "AniDbEpisodeFileXrefs"
        ],
        "operationId": "ShizouHttpClient_AniDbEpisodeFileXrefsGet",
        "responses": {
          "200": {
            "description": "OK"
          },
          "401": {
            "description": "Unauthorized"
          }
        }
      }
    },
    "/api/AniDbEpisodeFileXrefs/ByEpisodeId/{id}": {
      "get": {
        "tags": [
          "AniDbEpisodeFileXrefs"
        ],
        "operationId": "ShizouHttpClient_AniDbEpisodeFileXrefsByEpisodeId",
        "parameters": [
          {
            "name": "id",
            "in": "path",
            "required": true,
            "schema": {
              "type": "integer",
              "format": "int32"
            }
          }
        ],
        "responses": {
          "200": {
            "description": "OK",
            "content": {
              "application/json": {
                "schema": {
                  "type": "array",
                  "items": {
                    "$ref": "#/components/schemas/AniDbEpisodeFileXref"
                  }
                }
              }
            }
          },
          "404": {
            "description": "Not Found"
          },
          "401": {
            "description": "Unauthorized"
          }
        }
      }
    },
    "/api/AniDbEpisodeFileXrefs/ByAniDbFileId/{id}": {
      "get": {
        "tags": [
          "AniDbEpisodeFileXrefs"
        ],
        "operationId": "ShizouHttpClient_AniDbEpisodeFileXrefsByAniDbFileId",
        "parameters": [
          {
            "name": "id",
            "in": "path",
            "required": true,
            "schema": {
              "type": "integer",
              "format": "int32"
            }
          }
        ],
        "responses": {
          "200": {
            "description": "OK",
            "content": {
              "application/json": {
                "schema": {
                  "type": "array",
                  "items": {
                    "$ref": "#/components/schemas/AniDbEpisodeFileXref"
                  }
                }
              }
            }
          },
          "404": {
            "description": "Not Found"
          },
          "401": {
            "description": "Unauthorized"
          }
        }
      }
    },
    "/api/AniDbEpisodeFileXrefs/ByAniDbAnimeId/{id}": {
      "get": {
        "tags": [
          "AniDbEpisodeFileXrefs"
        ],
        "operationId": "ShizouHttpClient_AniDbEpisodeFileXrefsByAniDbAnimeId",
        "parameters": [
          {
            "name": "id",
            "in": "path",
            "required": true,
            "schema": {
              "type": "integer",
              "format": "int32"
            }
          }
        ],
        "responses": {
          "200": {
            "description": "OK",
            "content": {
              "application/json": {
                "schema": {
                  "type": "array",
                  "items": {
                    "$ref": "#/components/schemas/AniDbEpisodeFileXref"
                  }
                }
              }
            }
          },
          "404": {
            "description": "Not Found"
          },
          "401": {
            "description": "Unauthorized"
          }
        }
      }
    },
    "/api/AniDbEpisodes": {
      "get": {
        "tags": [
          "AniDbEpisodes"
        ],
        "operationId": "ShizouHttpClient_AniDbEpisodesGet",
        "responses": {
          "200": {
            "description": "OK",
            "content": {
              "application/json": {
                "schema": {
                  "type": "array",
                  "items": {
                    "$ref": "#/components/schemas/AniDbEpisode"
                  }
                }
              }
            }
          },
          "401": {
            "description": "Unauthorized"
          }
        }
      }
    },
    "/api/AniDbEpisodes/{id}": {
      "get": {
        "tags": [
          "AniDbEpisodes"
        ],
        "operationId": "ShizouHttpClient_AniDbEpisodesGet",
        "parameters": [
          {
            "name": "id",
            "in": "path",
            "required": true,
            "schema": {
              "type": "integer",
              "format": "int32"
            }
          }
        ],
        "responses": {
          "200": {
            "description": "OK",
            "content": {
              "application/json": {
                "schema": {
                  "$ref": "#/components/schemas/AniDbEpisode"
                }
              }
            }
          },
          "404": {
            "description": "Not Found"
          },
          "401": {
            "description": "Unauthorized"
          }
        }
      }
    },
    "/api/AniDbEpisodes/ByAniDbFileId/{id}": {
      "get": {
        "tags": [
          "AniDbEpisodes"
        ],
        "operationId": "ShizouHttpClient_AniDbEpisodesByAniDbFileId",
        "parameters": [
          {
            "name": "id",
            "in": "path",
            "required": true,
            "schema": {
              "type": "integer",
              "format": "int32"
            }
          }
        ],
        "responses": {
          "200": {
            "description": "OK",
            "content": {
              "application/json": {
                "schema": {
                  "type": "array",
                  "items": {
                    "$ref": "#/components/schemas/AniDbEpisode"
                  }
                }
              }
            }
          },
          "404": {
            "description": "Not Found"
          },
          "401": {
            "description": "Unauthorized"
          }
        }
      }
    },
    "/api/AniDbEpisodes/ByAniDbAnimeId/{id}": {
      "get": {
        "tags": [
          "AniDbEpisodes"
        ],
        "operationId": "ShizouHttpClient_AniDbEpisodesByAniDbAnimeId",
        "parameters": [
          {
            "name": "id",
            "in": "path",
            "required": true,
            "schema": {
              "type": "integer",
              "format": "int32"
            }
          }
        ],
        "responses": {
          "200": {
            "description": "OK",
            "content": {
              "application/json": {
                "schema": {
                  "type": "array",
                  "items": {
                    "$ref": "#/components/schemas/AniDbEpisode"
                  }
                }
              }
            }
          },
          "404": {
            "description": "Not Found"
          },
          "401": {
            "description": "Unauthorized"
          }
        }
      }
    },
    "/api/AniDbFiles": {
      "get": {
        "tags": [
          "AniDbFiles"
        ],
        "operationId": "ShizouHttpClient_AniDbFilesGet",
        "responses": {
          "200": {
            "description": "OK",
            "content": {
              "application/json": {
                "schema": {
                  "type": "array",
                  "items": {
                    "$ref": "#/components/schemas/AniDbFile"
                  }
                }
              }
            }
          },
          "401": {
            "description": "Unauthorized"
          }
        }
      }
    },
    "/api/AniDbFiles/{id}": {
      "get": {
        "tags": [
          "AniDbFiles"
        ],
        "operationId": "ShizouHttpClient_AniDbFilesGet",
        "parameters": [
          {
            "name": "id",
            "in": "path",
            "required": true,
            "schema": {
              "type": "integer",
              "format": "int32"
            }
          }
        ],
        "responses": {
          "200": {
            "description": "OK",
            "content": {
              "application/json": {
                "schema": {
                  "$ref": "#/components/schemas/AniDbFile"
                }
              }
            }
          },
          "404": {
            "description": "Not Found"
          },
          "401": {
            "description": "Unauthorized"
          }
        }
      }
    },
    "/api/AniDbFiles/{id}/MarkWatched": {
      "put": {
        "tags": [
          "AniDbFiles"
        ],
        "operationId": "ShizouHttpClient_AniDbFilesMarkWatched",
        "parameters": [
          {
            "name": "id",
            "in": "path",
            "required": true,
            "schema": {
              "type": "integer",
              "format": "int32"
            }
          }
        ],
        "responses": {
          "200": {
            "description": "OK"
          },
          "404": {
            "description": "Not Found"
          },
          "401": {
            "description": "Unauthorized"
          }
        }
      }
    },
    "/api/AniDbFiles/{id}/MarkUnwatched": {
      "put": {
        "tags": [
          "AniDbFiles"
        ],
        "operationId": "ShizouHttpClient_AniDbFilesMarkUnwatched",
        "parameters": [
          {
            "name": "id",
            "in": "path",
            "required": true,
            "schema": {
              "type": "integer",
              "format": "int32"
            }
          }
        ],
        "responses": {
          "200": {
            "description": "OK"
          },
          "404": {
            "description": "Not Found"
          },
          "401": {
            "description": "Unauthorized"
          }
        }
      }
    },
    "/api/AniDbFiles/ByAniDbAnimeId/{id}": {
      "get": {
        "tags": [
          "AniDbFiles"
        ],
        "operationId": "ShizouHttpClient_AniDbFilesByAniDbAnimeId",
        "parameters": [
          {
            "name": "id",
            "in": "path",
            "required": true,
            "schema": {
              "type": "integer",
              "format": "int32"
            }
          }
        ],
        "responses": {
          "200": {
            "description": "OK",
            "content": {
              "application/json": {
                "schema": {
                  "type": "array",
                  "items": {
                    "$ref": "#/components/schemas/AniDbFile"
                  }
                }
              }
            }
          },
          "404": {
            "description": "Not Found"
          },
          "401": {
            "description": "Unauthorized"
          }
        }
      }
    },
    "/api/AniDbNormalFiles": {
      "get": {
        "tags": [
          "AniDbNormalFiles"
        ],
        "operationId": "ShizouHttpClient_AniDbNormalFilesGet",
        "responses": {
          "200": {
            "description": "OK",
            "content": {
              "application/json": {
                "schema": {
                  "type": "array",
                  "items": {
                    "$ref": "#/components/schemas/AniDbNormalFile"
                  }
                }
              }
            }
          },
          "401": {
            "description": "Unauthorized"
          }
        }
      }
    },
    "/api/AniDbNormalFiles/{id}": {
      "get": {
        "tags": [
          "AniDbNormalFiles"
        ],
        "operationId": "ShizouHttpClient_AniDbNormalFilesGet",
        "parameters": [
          {
            "name": "id",
            "in": "path",
            "required": true,
            "schema": {
              "type": "integer",
              "format": "int32"
            }
          }
        ],
        "responses": {
          "200": {
            "description": "OK",
            "content": {
              "application/json": {
                "schema": {
                  "$ref": "#/components/schemas/AniDbNormalFile"
                }
              }
            }
          },
          "404": {
            "description": "Not Found"
          },
          "401": {
            "description": "Unauthorized"
          }
        }
      }
    },
    "/api/AniDbNormalFiles/ByAniDbAnimeId/{id}": {
      "get": {
        "tags": [
          "AniDbNormalFiles"
        ],
        "operationId": "ShizouHttpClient_AniDbNormalFilesByAniDbAnimeId",
        "parameters": [
          {
            "name": "id",
            "in": "path",
            "required": true,
            "schema": {
              "type": "integer",
              "format": "int32"
            }
          }
        ],
        "responses": {
          "200": {
            "description": "OK",
            "content": {
              "application/json": {
                "schema": {
                  "type": "array",
                  "items": {
                    "$ref": "#/components/schemas/AniDbNormalFile"
                  }
                }
              }
            }
          },
          "404": {
            "description": "Not Found"
          },
          "401": {
            "description": "Unauthorized"
          }
        }
      }
    },
    "/api/Command/PingAniDb": {
      "put": {
        "tags": [
          "Command"
        ],
        "operationId": "ShizouHttpClient_CommandPingAniDb",
        "responses": {
          "200": {
            "description": "OK"
          },
          "401": {
            "description": "Unauthorized"
          }
        }
      }
    },
    "/api/Command/SyncMyList": {
      "put": {
        "tags": [
          "Command"
        ],
        "operationId": "ShizouHttpClient_CommandSyncMyList",
        "responses": {
          "200": {
            "description": "OK"
          },
          "401": {
            "description": "Unauthorized"
          }
        }
      }
    },
    "/api/Command/UpdateMyList": {
      "put": {
        "tags": [
          "Command"
        ],
        "operationId": "ShizouHttpClient_CommandUpdateMyList",
        "requestBody": {
          "content": {
            "application/json": {
              "schema": {
                "allOf": [
                  {
                    "$ref": "#/components/schemas/UpdateMyListArgs"
                  }
                ]
              }
            }
          }
        },
        "responses": {
          "200": {
            "description": "OK"
          },
          "401": {
            "description": "Unauthorized"
          }
        }
      }
    },
    "/api/FileServer/{ed2K}": {
      "get": {
        "tags": [
          "FileServer"
        ],
        "operationId": "ShizouHttpClient_FileServerGet",
        "parameters": [
          {
            "name": "ed2K",
            "in": "path",
            "required": true,
            "schema": {
              "type": "string"
            }
          }
        ],
        "responses": {
          "404": {
            "description": "Not Found"
          },
          "416": {
            "description": "Range Not Satisfiable"
          },
          "206": {
            "description": "Partial Content",
            "content": {
              "application/octet-stream": {
                "schema": {
                  "type": "string",
                  "format": "binary"
                }
              }
            }
          },
          "200": {
            "description": "OK",
            "content": {
              "application/octet-stream": {
                "schema": {
                  "type": "string",
                  "format": "binary"
                }
              }
            }
          },
          "401": {
            "description": "Unauthorized"
          }
        }
      }
    },
    "/api/FileServer/{ed2K}/Playlist": {
      "get": {
        "tags": [
          "FileServer"
        ],
        "operationId": "ShizouHttpClient_FileServerGetPlaylist",
        "parameters": [
          {
            "name": "ed2K",
            "in": "path",
            "required": true,
            "schema": {
              "type": "string"
            }
          },
          {
            "name": "single",
            "in": "query",
            "schema": {
              "type": "boolean"
            }
          }
        ],
        "responses": {
          "404": {
            "description": "Not Found"
          },
          "200": {
            "description": "OK",
            "content": {
              "application/x-mpegurl": {
                "schema": {
                  "type": "string",
                  "format": "binary"
                }
              }
            }
          },
          "401": {
            "description": "Unauthorized"
          }
        }
      }
    },
    "/api/FileServer/{ed2k}/Fonts/{fontName}": {
      "get": {
        "tags": [
          "FileServer"
        ],
        "operationId": "ShizouHttpClient_FileServerGetFont",
        "parameters": [
          {
            "name": "ed2K",
            "in": "path",
            "required": true,
            "schema": {
              "type": "string"
            }
          },
          {
            "name": "fontName",
            "in": "path",
            "required": true,
            "schema": {
              "type": "string"
            }
          }
        ],
        "responses": {
          "404": {
            "description": "Not Found"
          },
          "200": {
            "description": "OK",
            "content": {
              "font/ttf": {
                "schema": {
                  "type": "string",
                  "format": "binary"
                }
              },
              "font/otf": {
                "schema": {
                  "type": "string",
                  "format": "binary"
                }
              }
            }
          },
          "401": {
            "description": "Unauthorized"
          }
        }
      }
    },
    "/api/FileServer/{ed2K}/Subtitles/{index}": {
      "get": {
        "tags": [
          "FileServer"
        ],
        "operationId": "ShizouHttpClient_FileServerGetSubtitle",
        "parameters": [
          {
            "name": "ed2K",
            "in": "path",
            "required": true,
            "schema": {
              "type": "string"
            }
          },
          {
            "name": "index",
            "in": "path",
            "required": true,
            "schema": {
              "type": "integer",
              "format": "int32"
            }
          }
        ],
        "responses": {
          "404": {
            "description": "Not Found"
          },
          "200": {
            "description": "OK",
            "content": {
              "text/x-ssa": {
                "schema": {
                  "type": "string",
                  "format": "binary"
                }
              }
            }
          },
          "401": {
            "description": "Unauthorized"
          }
        }
      }
    },
    "/api/FileWatchedStates": {
      "get": {
        "tags": [
          "FileWatchedStates"
        ],
        "operationId": "ShizouHttpClient_FileWatchedStatesGet",
        "responses": {
          "200": {
            "description": "OK",
            "content": {
              "application/json": {
                "schema": {
                  "type": "array",
                  "items": {
                    "$ref": "#/components/schemas/FileWatchedState"
                  }
                }
              }
            }
          },
          "401": {
            "description": "Unauthorized"
          }
        }
      },
      "put": {
        "tags": [
          "FileWatchedStates"
        ],
        "operationId": "ShizouHttpClient_FileWatchedStatesPut",
        "requestBody": {
          "content": {
            "application/json": {
              "schema": {
                "allOf": [
                  {
                    "$ref": "#/components/schemas/FileWatchedState"
                  }
                ]
              }
            }
          }
        },
        "responses": {
          "204": {
            "description": "No Content"
          },
          "404": {
            "description": "Not Found"
          },
          "400": {
            "description": "Bad Request",
            "content": {
              "application/json": {
                "schema": {
                  "$ref": "#/components/schemas/ProblemDetails"
                }
              }
            }
          },
          "401": {
            "description": "Unauthorized"
          }
        }
      },
      "post": {
        "tags": [
          "FileWatchedStates"
        ],
        "operationId": "ShizouHttpClient_FileWatchedStatesPost",
        "requestBody": {
          "content": {
            "application/json": {
              "schema": {
                "allOf": [
                  {
                    "$ref": "#/components/schemas/FileWatchedState"
                  }
                ]
              }
            }
          }
        },
        "responses": {
          "201": {
            "description": "Created",
            "content": {
              "application/json": {
                "schema": {
                  "$ref": "#/components/schemas/FileWatchedState"
                }
              }
            }
          },
          "400": {
            "description": "Bad Request",
            "content": {
              "application/json": {
                "schema": {
                  "$ref": "#/components/schemas/ProblemDetails"
                }
              }
            }
          },
          "409": {
            "description": "Conflict"
          },
          "401": {
            "description": "Unauthorized"
          }
        }
      }
    },
    "/api/FileWatchedStates/{id}": {
      "get": {
        "tags": [
          "FileWatchedStates"
        ],
        "operationId": "ShizouHttpClient_FileWatchedStatesGet",
        "parameters": [
          {
            "name": "id",
            "in": "path",
            "required": true,
            "schema": {
              "type": "integer",
              "format": "int32"
            }
          }
        ],
        "responses": {
          "200": {
            "description": "OK",
            "content": {
              "application/json": {
                "schema": {
                  "$ref": "#/components/schemas/FileWatchedState"
                }
              }
            }
          },
          "404": {
            "description": "Not Found"
          },
          "401": {
            "description": "Unauthorized"
          }
        }
      },
      "delete": {
        "tags": [
          "FileWatchedStates"
        ],
        "operationId": "ShizouHttpClient_FileWatchedStatesDelete",
        "parameters": [
          {
            "name": "id",
            "in": "path",
            "required": true,
            "schema": {
              "type": "integer",
              "format": "int32"
            }
          }
        ],
        "responses": {
          "204": {
            "description": "Entity deleted"
          },
          "404": {
            "description": "Not Found"
          },
          "400": {
            "description": "Bad Request",
            "content": {
              "application/json": {
                "schema": {
                  "$ref": "#/components/schemas/ProblemDetails"
                }
              }
            }
          },
          "401": {
            "description": "Unauthorized"
          }
        }
      }
    },
    "/api/Images/MissingAnimePosters": {
      "put": {
        "tags": [
          "Images"
        ],
        "operationId": "ShizouHttpClient_ImagesGetMissingAnimePosters",
        "responses": {
          "200": {
            "description": "OK"
          },
          "401": {
            "description": "Unauthorized"
          }
        }
      }
    },
    "/api/Images/AnimePosters/{animeId}": {
      "get": {
        "tags": [
          "Images"
        ],
        "operationId": "ShizouHttpClient_ImagesGetAnimePoster",
        "parameters": [
          {
            "name": "animeId",
            "in": "path",
            "required": true,
            "schema": {
              "type": "integer",
              "format": "int32"
            }
          }
        ],
        "responses": {
          "200": {
            "description": "OK",
            "content": {
              "image/gif": {
                "schema": {
                  "type": "string",
                  "format": "binary"
                }
              },
              "image/png": {
                "schema": {
                  "type": "string",
                  "format": "binary"
                }
              },
              "image/jpeg": {
                "schema": {
                  "type": "string",
                  "format": "binary"
                }
              }
            }
          },
          "404": {
            "description": "Not Found"
          },
          "401": {
            "description": "Unauthorized"
          }
        }
      }
    },
    "/api/Images/CreatorImages/{creatorId}": {
      "get": {
        "tags": [
          "Images"
        ],
        "operationId": "ShizouHttpClient_ImagesGetCreatorImage",
        "parameters": [
          {
            "name": "creatorId",
            "in": "path",
            "required": true,
            "schema": {
              "type": "integer",
              "format": "int32"
            }
          }
        ],
        "responses": {
          "200": {
            "description": "OK",
            "content": {
              "image/gif": {
                "schema": {
                  "type": "string",
                  "format": "binary"
                }
              },
              "image/png": {
                "schema": {
                  "type": "string",
                  "format": "binary"
                }
              },
              "image/jpeg": {
                "schema": {
                  "type": "string",
                  "format": "binary"
                }
              }
            }
          },
          "404": {
            "description": "Not Found"
          },
          "401": {
            "description": "Unauthorized"
          }
        }
      }
    },
    "/api/Images/EpisodeThumbnails/{episodeId}": {
      "get": {
        "tags": [
          "Images"
        ],
        "operationId": "ShizouHttpClient_ImagesGetEpisodeThumbnail",
        "parameters": [
          {
            "name": "episodeId",
            "in": "path",
            "required": true,
            "schema": {
              "type": "integer",
              "format": "int32"
            }
          }
        ],
        "responses": {
          "200": {
            "description": "OK",
            "content": {
              "image/webp": {
                "schema": {
                  "type": "string",
                  "format": "binary"
                }
              }
            }
          },
          "404": {
            "description": "Not Found"
          },
          "401": {
            "description": "Unauthorized"
          }
        }
      }
    },
    "/api/Import/StartImport": {
      "put": {
        "tags": [
          "Import"
        ],
        "operationId": "ShizouHttpClient_ImportStartImport",
        "responses": {
          "200": {
            "description": "OK"
          },
          "401": {
            "description": "Unauthorized"
          }
        }
      }
    },
    "/api/Import/ScanFolder/{id}": {
      "put": {
        "tags": [
          "Import"
        ],
        "operationId": "ShizouHttpClient_ImportScanFolder",
        "parameters": [
          {
            "name": "id",
            "in": "path",
            "required": true,
            "schema": {
              "type": "integer",
              "format": "int32"
            }
          }
        ],
        "responses": {
          "200": {
            "description": "OK"
          },
          "401": {
            "description": "Unauthorized"
          }
        }
      }
    },
    "/api/ImportFolders": {
      "get": {
        "tags": [
          "ImportFolders"
        ],
        "operationId": "ShizouHttpClient_ImportFoldersGet",
        "responses": {
          "200": {
            "description": "OK",
            "content": {
              "application/json": {
                "schema": {
                  "type": "array",
                  "items": {
                    "$ref": "#/components/schemas/ImportFolder"
                  }
                }
              }
            }
          },
          "401": {
            "description": "Unauthorized"
          }
        }
      },
      "put": {
        "tags": [
          "ImportFolders"
        ],
        "operationId": "ShizouHttpClient_ImportFoldersPut",
        "requestBody": {
          "content": {
            "application/json": {
              "schema": {
                "allOf": [
                  {
                    "$ref": "#/components/schemas/ImportFolder"
                  }
                ]
              }
            }
          }
        },
        "responses": {
          "204": {
            "description": "No Content"
          },
          "404": {
            "description": "Not Found"
          },
          "400": {
            "description": "Bad Request",
            "content": {
              "application/json": {
                "schema": {
                  "$ref": "#/components/schemas/ProblemDetails"
                }
              }
            }
          },
          "401": {
            "description": "Unauthorized"
          }
        }
      },
      "post": {
        "tags": [
          "ImportFolders"
        ],
        "operationId": "ShizouHttpClient_ImportFoldersPost",
        "requestBody": {
          "content": {
            "application/json": {
              "schema": {
                "allOf": [
                  {
                    "$ref": "#/components/schemas/ImportFolder"
                  }
                ]
              }
            }
          }
        },
        "responses": {
          "201": {
            "description": "Created",
            "content": {
              "application/json": {
                "schema": {
                  "$ref": "#/components/schemas/ImportFolder"
                }
              }
            }
          },
          "400": {
            "description": "Bad Request",
            "content": {
              "application/json": {
                "schema": {
                  "$ref": "#/components/schemas/ProblemDetails"
                }
              }
            }
          },
          "409": {
            "description": "Conflict"
          },
          "401": {
            "description": "Unauthorized"
          }
        }
      }
    },
    "/api/ImportFolders/{id}": {
      "get": {
        "tags": [
          "ImportFolders"
        ],
        "operationId": "ShizouHttpClient_ImportFoldersGet",
        "parameters": [
          {
            "name": "id",
            "in": "path",
            "required": true,
            "schema": {
              "type": "integer",
              "format": "int32"
            }
          }
        ],
        "responses": {
          "200": {
            "description": "OK",
            "content": {
              "application/json": {
                "schema": {
                  "$ref": "#/components/schemas/ImportFolder"
                }
              }
            }
          },
          "404": {
            "description": "Not Found"
          },
          "401": {
            "description": "Unauthorized"
          }
        }
      },
      "delete": {
        "tags": [
          "ImportFolders"
        ],
        "operationId": "ShizouHttpClient_ImportFoldersDelete",
        "parameters": [
          {
            "name": "id",
            "in": "path",
            "required": true,
            "schema": {
              "type": "integer",
              "format": "int32"
            }
          }
        ],
        "responses": {
          "204": {
            "description": "Entity deleted"
          },
          "404": {
            "description": "Not Found"
          },
          "400": {
            "description": "Bad Request",
            "content": {
              "application/json": {
                "schema": {
                  "$ref": "#/components/schemas/ProblemDetails"
                }
              }
            }
          },
          "401": {
            "description": "Unauthorized"
          }
        }
      }
    },
    "/api/ImportFolders/path/{path}": {
      "get": {
        "tags": [
          "ImportFolders"
        ],
        "operationId": "ShizouHttpClient_ImportFoldersGetByPath",
        "parameters": [
          {
            "name": "path",
            "in": "path",
            "required": true,
            "schema": {
              "type": "string"
            }
          }
        ],
        "responses": {
          "200": {
            "description": "OK",
            "content": {
              "application/json": {
                "schema": {
                  "$ref": "#/components/schemas/ImportFolder"
                }
              }
            }
          },
          "404": {
            "description": "Not Found"
          },
          "401": {
            "description": "Unauthorized"
          }
        }
      }
    },
    "/api/LocalFiles": {
      "get": {
        "tags": [
          "LocalFiles"
        ],
        "operationId": "ShizouHttpClient_LocalFilesGet",
        "responses": {
          "200": {
            "description": "OK",
            "content": {
              "application/json": {
                "schema": {
                  "type": "array",
                  "items": {
                    "$ref": "#/components/schemas/LocalFile"
                  }
                }
              }
            }
          },
          "401": {
            "description": "Unauthorized"
          }
        }
      }
    },
    "/api/LocalFiles/{id}": {
      "get": {
        "tags": [
          "LocalFiles"
        ],
        "operationId": "ShizouHttpClient_LocalFilesGet",
        "parameters": [
          {
            "name": "id",
            "in": "path",
            "required": true,
            "schema": {
              "type": "integer",
              "format": "int32"
            }
          }
        ],
        "responses": {
          "200": {
            "description": "OK",
            "content": {
              "application/json": {
                "schema": {
                  "$ref": "#/components/schemas/LocalFile"
                }
              }
            }
          },
          "404": {
            "description": "Not Found"
          },
          "401": {
            "description": "Unauthorized"
          }
        }
      }
    },
    "/api/LocalFiles/ProcessFile/{id}": {
      "put": {
        "tags": [
          "LocalFiles"
        ],
        "operationId": "ShizouHttpClient_LocalFilesProcessFile",
        "parameters": [
          {
            "name": "id",
            "in": "path",
            "required": true,
            "schema": {
              "type": "integer",
              "format": "int32"
            }
          }
        ],
        "responses": {
          "200": {
            "description": "OK"
          },
          "401": {
            "description": "Unauthorized"
          }
        }
      }
    },
    "/api/MyAnimeList/GetToken": {
      "get": {
        "tags": [
          "MyAnimeList"
        ],
        "operationId": "ShizouHttpClient_MyAnimeListGetToken",
        "parameters": [
          {
            "name": "code",
            "in": "query",
            "schema": {
              "type": "string"
            }
          },
          {
            "name": "state",
            "in": "query",
            "schema": {
              "type": "string"
            }
          }
        ],
        "responses": {
          "400": {
            "description": "Bad Request"
          },
          "409": {
            "description": "Conflict"
          },
          "200": {
            "description": "OK"
          },
          "401": {
            "description": "Unauthorized"
          }
        }
      }
    },
    "/api/MyAnimeList/Authenticate": {
      "get": {
        "tags": [
          "MyAnimeList"
        ],
        "operationId": "ShizouHttpClient_MyAnimeListAuthenticate",
        "responses": {
          "400": {
            "description": "Bad Request"
          },
          "200": {
            "description": "OK",
            "content": {
              "application/json": {
                "schema": {
                  "type": "string"
                }
              }
            }
          },
          "401": {
            "description": "Unauthorized"
          }
        }
      }
    },
    "/api/Options": {
      "get": {
        "tags": [
          "Options"
        ],
        "operationId": "ShizouHttpClient_OptionsGet",
        "responses": {
          "200": {
            "description": "OK",
            "content": {
              "application/json": {
                "schema": {
                  "$ref": "#/components/schemas/ShizouOptions"
                }
              }
            }
          },
          "401": {
            "description": "Unauthorized"
          }
        }
      },
      "put": {
        "tags": [
          "Options"
        ],
        "operationId": "ShizouHttpClient_OptionsSave",
        "requestBody": {
          "content": {
            "application/json": {
              "schema": {
                "allOf": [
                  {
                    "$ref": "#/components/schemas/ShizouOptions"
                  }
                ]
              }
            }
          }
        },
        "responses": {
          "200": {
            "description": "OK"
          },
          "401": {
            "description": "Unauthorized"
          }
        }
      }
    },
    "/api/Queues/{queueType}/Pause": {
      "put": {
        "tags": [
          "Queues"
        ],
        "operationId": "ShizouHttpClient_QueuesPause",
        "parameters": [
          {
            "name": "queueType",
            "in": "path",
            "required": true,
            "schema": {
              "allOf": [
                {
                  "$ref": "#/components/schemas/QueueType"
                }
              ]
            }
          }
        ],
        "responses": {
          "200": {
            "description": "OK"
          },
          "400": {
            "description": "Bad Request"
          },
          "401": {
            "description": "Unauthorized"
          }
        }
      }
    },
    "/api/Queues/{queueType}/Clear": {
      "put": {
        "tags": [
          "Queues"
        ],
        "operationId": "ShizouHttpClient_QueuesClear",
        "parameters": [
          {
            "name": "queueType",
            "in": "path",
            "required": true,
            "schema": {
              "allOf": [
                {
                  "$ref": "#/components/schemas/QueueType"
                }
              ]
            }
          }
        ],
        "responses": {
          "200": {
            "description": "OK"
          },
          "400": {
            "description": "Bad Request"
          },
          "401": {
            "description": "Unauthorized"
          }
        }
      }
    },
    "/api/Queues/{queueType}/Current": {
      "get": {
        "tags": [
          "Queues"
        ],
        "operationId": "ShizouHttpClient_QueuesCurrent",
        "parameters": [
          {
            "name": "queueType",
            "in": "path",
            "required": true,
            "schema": {
              "allOf": [
                {
                  "$ref": "#/components/schemas/QueueType"
                }
              ]
            }
          }
        ],
        "responses": {
          "200": {
            "description": "OK",
            "content": {
              "application/json": {
                "schema": {
                  "$ref": "#/components/schemas/CommandArgsICommand"
                }
              }
            }
          },
          "204": {
            "description": "No Content"
          },
          "400": {
            "description": "Bad Request"
          },
          "401": {
            "description": "Unauthorized"
          }
        }
      }
    },
    "/api/Queues/{queueType}/Unpause": {
      "put": {
        "tags": [
          "Queues"
        ],
        "operationId": "ShizouHttpClient_QueuesUnpause",
        "parameters": [
          {
            "name": "queueType",
            "in": "path",
            "required": true,
            "schema": {
              "allOf": [
                {
                  "$ref": "#/components/schemas/QueueType"
                }
              ]
            }
          }
        ],
        "responses": {
          "200": {
            "description": "OK"
          },
          "409": {
            "description": "Conflict",
            "content": {
              "application/json": {
                "schema": {
                  "$ref": "#/components/schemas/ProblemDetails"
                }
              }
            }
          },
          "400": {
            "description": "Bad Request"
          },
          "401": {
            "description": "Unauthorized"
          }
        }
      }
    },
    "/api/Queues/{queueType}/PauseState": {
      "get": {
        "tags": [
          "Queues"
        ],
        "operationId": "ShizouHttpClient_QueuesPauseState",
        "parameters": [
          {
            "name": "queueType",
            "in": "path",
            "required": true,
            "schema": {
              "allOf": [
                {
                  "$ref": "#/components/schemas/QueueType"
                }
              ]
            }
          }
        ],
        "responses": {
          "200": {
            "description": "OK",
            "content": {
              "application/json": {
                "schema": {
                  "$ref": "#/components/schemas/PauseResult"
                }
              }
            }
          },
          "400": {
            "description": "Bad Request"
          },
          "401": {
            "description": "Unauthorized"
          }
        }
      }
    },
    "/api/Queues/{queueType}/QueuedRequests": {
      "get": {
        "tags": [
          "Queues"
        ],
        "operationId": "ShizouHttpClient_QueuesQueuedRequests",
        "parameters": [
          {
            "name": "queueType",
            "in": "path",
            "required": true,
            "schema": {
              "allOf": [
                {
                  "$ref": "#/components/schemas/QueueType"
                }
              ]
            }
          }
        ],
        "responses": {
          "200": {
            "description": "OK",
            "content": {
              "application/json": {
                "schema": {
                  "type": "array",
                  "items": {
                    "$ref": "#/components/schemas/CommandRequest"
                  }
                }
              }
            }
          },
          "400": {
            "description": "Bad Request"
          },
          "401": {
            "description": "Unauthorized"
          }
        }
      }
    }
  },
  "components": {
    "schemas": {
      "AniDbAnime": {
        "required": [
          "airDate",
          "animeType",
          "description",
          "endDate",
          "episodeCount",
          "id",
          "imageFilename",
          "rating",
          "restricted",
          "tags",
          "titleEnglish",
          "titleOriginal",
          "titleTranscription",
          "updated"
        ],
        "type": "object",
        "properties": {
          "id": {
            "type": "integer",
            "format": "int32"
          },
          "titleTranscription": {
            "type": "string"
          },
          "titleOriginal": {
            "type": "string",
            "nullable": true
          },
          "titleEnglish": {
            "type": "string",
            "nullable": true
          },
          "animeType": {
            "allOf": [
              {
                "$ref": "#/components/schemas/AnimeType"
              }
            ]
          },
          "episodeCount": {
            "type": "integer",
            "format": "int32",
            "nullable": true
          },
          "airDate": {
            "type": "string",
            "format": "date",
            "nullable": true
          },
          "endDate": {
            "type": "string",
            "format": "date",
            "nullable": true
          },
          "description": {
            "type": "string",
            "nullable": true
          },
          "restricted": {
            "type": "boolean"
          },
          "imageFilename": {
            "type": "string",
            "nullable": true
          },
          "rating": {
            "type": "number",
            "format": "float",
            "nullable": true
          },
          "tags": {
            "type": "array",
            "items": {
              "type": "string"
            }
          },
          "updated": {
            "type": "string",
            "format": "date-time"
          },
          "aniDbUpdated": {
            "type": "string",
            "format": "date-time",
            "nullable": true
          }
        },
        "additionalProperties": false
      },
      "AniDbAudio": {
        "required": [
          "bitrate",
          "codec",
          "language"
        ],
        "type": "object",
        "properties": {
          "language": {
            "type": "string"
          },
          "codec": {
            "type": "string"
          },
          "bitrate": {
            "type": "integer",
            "format": "int32"
          }
        },
        "additionalProperties": false
      },
      "AniDbCharacter": {
        "required": [
          "id",
          "imageFilename",
          "name",
          "type"
        ],
        "type": "object",
        "properties": {
          "id": {
            "type": "integer",
            "format": "int32"
          },
          "name": {
            "type": "string"
          },
          "type": {
            "allOf": [
              {
                "$ref": "#/components/schemas/CharacterType"
              }
            ]
          },
          "imageFilename": {
            "type": "string",
            "nullable": true
          }
        },
        "additionalProperties": false
      },
      "AniDbCreator": {
        "required": [
          "id",
          "imageFilename",
          "name",
          "type"
        ],
        "type": "object",
        "properties": {
          "id": {
            "type": "integer",
            "format": "int32"
          },
          "type": {
            "allOf": [
              {
                "$ref": "#/components/schemas/CreatorType"
              }
            ]
          },
          "name": {
            "type": "string"
          },
          "imageFilename": {
            "type": "string",
            "nullable": true
          }
        },
        "additionalProperties": false
      },
      "AniDbCredit": {
        "required": [
          "aniDbAnimeId",
          "aniDbCreatorId",
          "id",
          "role"
        ],
        "type": "object",
        "properties": {
          "aniDbAnimeId": {
            "type": "integer",
            "format": "int32"
          },
          "id": {
            "type": "integer",
            "format": "int32"
          },
          "role": {
            "type": "string",
            "nullable": true
          },
          "aniDbCreatorId": {
            "type": "integer",
            "format": "int32"
          },
          "aniDbCreator": {
            "allOf": [
              {
                "$ref": "#/components/schemas/AniDbCreator"
              }
            ]
          },
          "aniDbCharacterId": {
            "type": "integer",
            "format": "int32",
            "nullable": true
          },
          "aniDbCharacter": {
            "allOf": [
              {
                "$ref": "#/components/schemas/AniDbCharacter"
              }
            ],
            "nullable": true
          }
        },
        "additionalProperties": false
      },
      "AniDbEpisode": {
        "required": [
          "airDate",
          "aniDbAnimeId",
          "durationMinutes",
          "episodeType",
          "id",
          "number",
          "summary",
          "titleEnglish",
          "titleOriginal",
          "titleTranscription",
          "updated"
        ],
        "type": "object",
        "properties": {
          "id": {
            "type": "integer",
            "format": "int32"
          },
          "titleEnglish": {
            "type": "string"
          },
          "titleTranscription": {
            "type": "string",
            "nullable": true
          },
          "titleOriginal": {
            "type": "string",
            "nullable": true
          },
          "number": {
            "type": "integer",
            "format": "int32"
          },
          "episodeType": {
            "allOf": [
              {
                "$ref": "#/components/schemas/EpisodeType"
              }
            ]
          },
          "durationMinutes": {
            "type": "integer",
            "format": "int32",
            "nullable": true
          },
          "airDate": {
            "type": "string",
            "format": "date",
            "nullable": true
          },
          "summary": {
            "type": "string",
            "nullable": true
          },
          "updated": {
            "type": "string",
            "format": "date-time"
          },
          "epString": {
            "type": "string",
            "readOnly": true
          },
          "aniDbAnimeId": {
            "type": "integer",
            "format": "int32"
          }
        },
        "additionalProperties": false
      },
      "AniDbEpisodeFileXref": {
        "required": [
          "aniDbEpisodeId",
          "aniDbFileId"
        ],
        "type": "object",
        "properties": {
          "aniDbEpisodeId": {
            "type": "integer",
            "format": "int32"
          },
          "aniDbFileId": {
            "type": "integer",
            "format": "int32"
          }
        },
        "additionalProperties": false
      },
      "AniDbFile": {
        "required": [
          "id"
        ],
        "type": "object",
        "properties": {
          "id": {
            "type": "integer",
            "format": "int32"
          }
        },
        "additionalProperties": false
      },
      "AniDbNormalFile": {
        "required": [
          "censored",
          "chaptered",
          "crc",
          "deprecated",
          "durationSeconds",
          "ed2k",
          "fileName",
          "fileSize",
          "fileVersion",
          "id",
          "md5",
          "sha1",
          "source",
          "updated"
        ],
        "type": "object",
        "properties": {
          "id": {
            "type": "integer",
            "format": "int32"
          },
          "ed2k": {
            "type": "string"
          },
          "crc": {
            "type": "string",
            "nullable": true
          },
          "md5": {
            "type": "string",
            "nullable": true
          },
          "sha1": {
            "type": "string",
            "nullable": true
          },
          "fileSize": {
            "type": "integer",
            "format": "int64"
          },
          "durationSeconds": {
            "type": "integer",
            "format": "int32",
            "nullable": true
          },
          "source": {
            "type": "string",
            "nullable": true
          },
          "updated": {
            "type": "string",
            "format": "date-time"
          },
          "fileVersion": {
            "type": "integer",
            "format": "int32"
          },
          "fileName": {
            "type": "string"
          },
          "censored": {
            "type": "boolean",
            "nullable": true
          },
          "deprecated": {
            "type": "boolean"
          },
          "chaptered": {
            "type": "boolean"
          },
          "aniDbGroupId": {
            "type": "integer",
            "format": "int32",
            "nullable": true
          },
          "video": {
            "allOf": [
              {
                "$ref": "#/components/schemas/AniDbVideo"
              }
            ],
            "nullable": true
          },
          "audio": {
            "type": "array",
            "items": {
              "$ref": "#/components/schemas/AniDbAudio"
            }
          },
          "subtitles": {
            "type": "array",
            "items": {
              "$ref": "#/components/schemas/AniDbSubtitle"
            }
          }
        },
        "additionalProperties": false
      },
      "AniDbOptions": {
        "required": [
          "username"
        ],
        "type": "object",
        "properties": {
          "username": {
            "maxLength": 16,
            "minLength": 3,
            "type": "string"
          },
          "password": {
            "type": "string"
          },
          "serverHost": {
            "type": "string"
          },
          "imageServerHost": {
            "type": "string",
            "nullable": true
          },
          "httpServerPort": {
            "type": "integer",
            "format": "int32"
          },
          "udpServerPort": {
            "type": "integer",
            "format": "int32"
          },
          "udpClientPort": {
            "type": "integer",
            "format": "int32"
          },
          "myList": {
            "allOf": [
              {
                "$ref": "#/components/schemas/MyListOptions"
              }
            ]
          },
          "fetchRelationDepth": {
            "type": "integer",
            "format": "int32"
          },
          "avDump": {
            "allOf": [
              {
                "$ref": "#/components/schemas/AvDumpOptions"
              }
            ]
          }
        },
        "additionalProperties": false
      },
      "AniDbSubtitle": {
        "required": [
          "language"
        ],
        "type": "object",
        "properties": {
          "language": {
            "type": "string"
          }
        },
        "additionalProperties": false
      },
      "AniDbVideo": {
        "required": [
          "bitRate",
          "codec",
          "colorDepth",
          "height",
          "width"
        ],
        "type": "object",
        "properties": {
          "codec": {
            "type": "string"
          },
          "bitRate": {
            "type": "integer",
            "format": "int32"
          },
          "width": {
            "type": "integer",
            "format": "int32"
          },
          "height": {
            "type": "integer",
            "format": "int32"
          },
          "colorDepth": {
            "type": "integer",
            "format": "int32"
          }
        },
        "additionalProperties": false
      },
      "AnimeType": {
        "enum": [
          "Unknown",
          "Movie",
          "Ova",
          "TvSeries",
          "TvSpecial",
          "Web",
          "Other",
          "MusicVideo"
        ],
        "type": "string"
      },
      "AvDumpOptions": {
        "type": "object",
        "properties": {
          "udpKey": {
            "type": "string",
            "nullable": true
          },
          "udpClientPort": {
            "type": "integer",
            "format": "int32"
          }
        },
        "additionalProperties": false
      },
      "CharacterType": {
        "enum": [
          "Unknown",
          "Character",
          "Mecha",
          "Organization",
          "Vehicle"
        ],
        "type": "string"
      },
      "CollectionViewOptions": {
        "type": "object",
        "properties": {
          "enabled": {
            "type": "boolean"
          },
          "path": {
            "type": "string"
          }
        },
        "additionalProperties": false
      },
      "CommandArgs": {
        "type": "object",
        "additionalProperties": false
      },
      "CommandArgsICommand": {
        "type": "object",
        "properties": {
          "commandId": {
            "type": "string",
            "readOnly": true
          },
          "completed": {
            "type": "boolean",
            "readOnly": true
          },
          "commandArgs": {
            "allOf": [
              {
                "$ref": "#/components/schemas/CommandArgs"
              }
            ],
            "nullable": true,
            "readOnly": true
          }
        },
        "additionalProperties": false
      },
      "CommandPriority": {
        "enum": [
          "Invalid",
          "Urgent",
          "High",
          "Normal",
          "Low"
        ],
        "type": "string"
      },
      "CommandRequest": {
        "required": [
          "commandArgs",
          "commandId",
          "priority",
          "queueType"
        ],
        "type": "object",
        "properties": {
          "id": {
            "type": "integer",
            "format": "int32"
          },
          "priority": {
            "allOf": [
              {
                "$ref": "#/components/schemas/CommandPriority"
              }
            ]
          },
          "queueType": {
            "allOf": [
              {
                "$ref": "#/components/schemas/QueueType"
              }
            ]
          },
          "commandId": {
            "type": "string"
          },
          "commandArgs": {
            "allOf": [
              {
                "$ref": "#/components/schemas/CommandArgs"
              }
            ]
          }
        },
        "additionalProperties": false
      },
      "CreatorType": {
        "enum": [
          "Unknown",
          "Person",
          "Company",
          "Collaboration",
          "Other"
        ],
        "type": "string"
      },
      "EpisodeType": {
        "enum": [
          "Episode",
          "Special",
          "Credits",
          "Trailer",
          "Parody",
          "Other"
        ],
        "type": "string"
      },
      "FileWatchedState": {
        "required": [
          "aniDbFileId",
          "watched",
          "watchedUpdated"
        ],
        "type": "object",
        "properties": {
          "aniDbFileId": {
            "type": "integer",
            "format": "int32"
          },
          "aniDbFile": {
            "allOf": [
              {
                "$ref": "#/components/schemas/AniDbFile"
              }
            ]
          },
          "watched": {
            "type": "boolean"
          },
          "watchedUpdated": {
            "type": "string",
            "format": "date-time",
            "nullable": true
          },
          "myListId": {
            "type": "integer",
            "format": "int32",
            "nullable": true
          }
        },
        "additionalProperties": false
      },
      "ImportFolder": {
        "required": [
          "name",
          "path"
        ],
        "type": "object",
        "properties": {
          "id": {
            "type": "integer",
            "format": "int32"
          },
          "name": {
            "minLength": 1,
            "type": "string"
          },
          "path": {
            "minLength": 1,
            "type": "string"
          },
          "scanOnImport": {
            "type": "boolean"
          }
        },
        "additionalProperties": false
      },
      "ImportOptions": {
        "type": "object",
        "properties": {
          "scanFileExtensions": {
            "type": "string"
          },
          "ffmpegPath": {
            "type": "string",
            "nullable": true
          },
          "ffprobePath": {
            "type": "string",
            "nullable": true
          }
        },
        "additionalProperties": false
      },
      "LocalFile": {
        "required": [
          "crc",
          "ed2k",
          "fileSize",
          "ignored",
          "pathTail",
          "signature"
        ],
        "type": "object",
        "properties": {
          "id": {
            "type": "integer",
            "format": "int32"
          },
          "ed2k": {
            "type": "string"
          },
          "crc": {
            "type": "string"
          },
          "fileSize": {
            "type": "integer",
            "format": "int64"
          },
          "signature": {
            "type": "string"
          },
          "ignored": {
            "type": "boolean"
          },
          "pathTail": {
            "type": "string"
          },
          "updated": {
            "type": "string",
            "format": "date-time",
            "nullable": true
          },
          "ed2KLink": {
            "type": "string",
            "readOnly": true
          },
          "importFolderId": {
            "type": "integer",
            "format": "int32",
            "nullable": true
          },
          "aniDbFileId": {
            "type": "integer",
            "format": "int32",
            "nullable": true
          }
        },
        "additionalProperties": false
      },
      "MyAnimeListOptions": {
        "type": "object",
        "properties": {
          "clientId": {
            "type": "string"
          }
        },
        "additionalProperties": false
      },
      "MyListOptions": {
        "type": "object",
        "properties": {
          "disableSync": {
            "type": "boolean"
          },
          "absentFileState": {
            "allOf": [
              {
                "$ref": "#/components/schemas/MyListState"
              }
            ]
          },
          "presentFileState": {
            "allOf": [
              {
                "$ref": "#/components/schemas/MyListState"
              }
            ]
          }
        },
        "additionalProperties": false
      },
      "MyListState": {
        "enum": [
          "Unknown",
          "Internal",
          "External",
          "Deleted",
          "Remote"
        ],
        "type": "string"
      },
      "PasswordModel": {
        "type": "object",
        "properties": {
          "password": {
            "type": "string"
          },
          "newPassword": {
            "type": "string"
          }
        },
        "additionalProperties": false
      },
      "PauseResult": {
        "type": "object",
        "properties": {
          "paused": {
            "type": "boolean"
          },
          "pauseReason": {
            "type": "string",
            "nullable": true
          }
        },
        "additionalProperties": false
      },
      "ProblemDetails": {
        "type": "object",
        "properties": {
          "type": {
            "type": "string",
            "nullable": true
          },
          "title": {
            "type": "string",
            "nullable": true
          },
          "status": {
            "type": "integer",
            "format": "int32",
            "nullable": true
          },
          "detail": {
            "type": "string",
            "nullable": true
          },
          "instance": {
            "type": "string",
            "nullable": true
          }
        },
        "additionalProperties": { }
      },
      "QueueType": {
        "enum": [
          "General",
          "AniDbUdp",
          "AniDbHttp",
          "Hash",
          "Image"
        ],
        "type": "string"
      },
      "ShizouOptions": {
        "type": "object",
        "properties": {
          "import": {
            "allOf": [
              {
                "$ref": "#/components/schemas/ImportOptions"
              }
            ]
          },
          "aniDb": {
            "allOf": [
              {
                "$ref": "#/components/schemas/AniDbOptions"
              }
            ]
          },
          "myAnimeList": {
            "allOf": [
              {
                "$ref": "#/components/schemas/MyAnimeListOptions"
              }
            ]
          },
          "collectionView": {
            "allOf": [
              {
                "$ref": "#/components/schemas/CollectionViewOptions"
              }
            ]
          }
        },
        "additionalProperties": false
      },
      "UpdateMyListArgs": {
        "type": "object",
        "properties": {
          "lid": {
            "type": "integer",
            "format": "int32"
          },
          "myListState": {
            "allOf": [
              {
                "$ref": "#/components/schemas/MyListState"
              }
            ]
          },
          "watched": {
            "type": "boolean",
            "nullable": true
          },
          "watchedDate": {
            "type": "string",
            "format": "date-time",
            "nullable": true
          }
        },
        "additionalProperties": false
      }
    }
  }
}